s27a_jbq/__constants__.py
s27a_jbq/__init__.py
s27a_jbq/__main__.py
s27a_jbq/game/__init__.py
s27a_jbq/game/extension.py
s27a_jbq/game/map.py
s27a_jbq/game/static.py
s27a_jbq/window/__init__.py
s27a_jbq/window/game_window.py
s27a_jbq/window/setting.py
s27a_jbq-1.1.0.dist-info/LICENSE
s27a_jbq-1.1.0.dist-info/METADATA
s27a_jbq-1.1.0.dist-info/WHEEL
s27a_jbq-1.1.0.dist-info/top_level.txt
s27a_jbq-1.1.0.dist-info/RECORD
