Metadata-Version: 2.1
Name: s27a-jbq
Version: 1.1.0
Summary: A board game with high degrees of freedom
Author-email: amf <xyf081202@163.com>
Project-URL: Homepage, https://github.com/amf14151/s27a_jbq
Project-URL: Bug Tracker, https://github.com/amf14151/s27a_jbq/issues
Classifier: Programming Language :: Python :: 3
Classifier: License :: OSI Approved :: MIT License
Classifier: Natural Language :: Chinese (Simplified)
Classifier: Operating System :: OS Independent
Requires-Python: >=3.7
License-File: LICENSE
